pydssp/__init__.py
pydssp/main.py
pydssp/pdbio.py
pydssp/pydssp_numpy.py
pydssp/pydssp_torch.py
pydssp-0.9.1.data/scripts/pydssp
pydssp-0.9.1.dist-info/LICENSE
pydssp-0.9.1.dist-info/METADATA
pydssp-0.9.1.dist-info/WHEEL
pydssp-0.9.1.dist-info/top_level.txt
pydssp-0.9.1.dist-info/RECORD
