Metadata-Version: 2.1
Name: pydssp
Version: 0.9.1
Summary: A simplified implementation of DSSP algorithm for PyTorch and NumPy
Home-page: https://github.com/ShintaroMinami/PyDSSP
Author: Shintaro Minami
License: MIT
Keywords: DSSP,Secondary Structure,Protein Structure
Classifier: License :: OSI Approved :: MIT License
Classifier: Programming Language :: Python :: 3.8
License-File: LICENSE
Requires-Dist: numpy
Requires-Dist: torch
Requires-Dist: einops
Requires-Dist: tqdm
